mltz/__init__.py
mltz/cv.py
mltz-0.1.1.dist-info/METADATA
mltz-0.1.1.dist-info/WHEEL
mltz-0.1.1.dist-info/licenses/LICENSE
mltz-0.1.1.dist-info/RECORD
